[
    {
        "address": "DEMI LUNE 1/9  7800ATH",
        "available_date": "2020-11-01",
        "bathroom_count": 1,
        "city": "ATH",
        "currency": "EUR",
        "description": "A +/- 300m de la gare et \u00e0 +/- 600m de la Grand Place, appartement 1chambre au 2i\u00e8me \u00e9tage, neuf, 1\u00e8re occupation\r\nDescription:\r\n2\u00e8me \u00e9tage: Hall d'entr\u00e9e, W.C. s\u00e9par\u00e9, buanderie, s\u00e9jour + cuisine ouverte \u00e9vier simple bac-taques vitro-hotte-four-frigo- cong\u00e9lateur-lave-vaisselle, salle de bains - douche-lavabo -, une chambre \r\nExt\u00e9rieur : Terrasse \r\nLoyer: 560\u20ac + 60 \u20ac de charges communes + 60 \u20ac provision eau chaude et gaz\r\nLibre \u00e0 partir du 1er novembre 2020\r\n\r\n",
        "elevator": true,
        "external_id": "9027",
        "external_images_count": 7,
        "external_link": "https://www.athimmo.be/fr/a-louer/ath/appartement-560-\u20ac--60-\u20ac-charges-communes--60-\u20ac-eau-chaude-et-gaz/9027",
        "external_source": "Athimmo2000Spider",
        "images": [
            "https://i4h6y2e7.stackpathcdn.com/athimmo.public/9027AL.jpg?637374972798310000",
            "https://i4h6y2e7.stackpathcdn.com/athimmo.public/9027BL.jpg?637374972792550000",
            "https://i4h6y2e7.stackpathcdn.com/athimmo.public/9027CL.jpg?637374972849590000",
            "https://i4h6y2e7.stackpathcdn.com/athimmo.public/9027DL.jpg?637374972902590000",
            "https://i4h6y2e7.stackpathcdn.com/athimmo.public/9027EL.jpg?637374972775080000",
            "https://i4h6y2e7.stackpathcdn.com/athimmo.public/9027FL.jpg?637374972866920000",
            "https://i4h6y2e7.stackpathcdn.com/athimmo.public/9027GL.jpg?637374972857400000"
        ],
        "landlord_email": "info@athimmo.be",
        "landlord_name": "Athimmo",
        "landlord_phone": "068 28 26 80",
        "latitude": "50.6345900000000000000000000",
        "longitude": "3.7823330000000000000000000",
        "property_type": "apartment",
        "rent": 560,
        "room_count": 1,
        "terrace": true,
        "title": "Appartement 560 \u20ac + 60 \u20ac CHARGES COMMUNES + 60 \u20ac eau chaude et gaz",
        "zipcode": "7800"
    },
    {
        "address": "rue de l'Abbaye 182/5  7800ATH",
        "available_date": "2021-01-01",
        "bathroom_count": 1,
        "city": "ATH",
        "currency": "EUR",
        "description": "Dans le quartier r\u00e9sidentiel de l'Abbaye, au premier \u00e9tage, bel appartement tr\u00e8s lumineux 1 chambre avec terrasse.PEB D (268 kWh/m\u00b2.an - 20150226009455)\r\nComposition:\r\nSous-sol : 1 cave ( 3m\u00b2)\r\n1er \u00e9tage : Hall, WC s\u00e9jour + cuisine \u2013 \u00e9vier simple, taques \u00e9lectriques, hotte, four, frigo (30 m\u00b2), salle-de-bains \u2013 baignoire, lavabo, 1 chambre (10 m\u00b2).\r\nLoyer: 525 \u20ac + 50 \u20ac de charges communes + 25 \u20ac provision eau\r\nLibre \u00e0 partir du 1er janvier 2021\r\n\r\n",
        "energy_label": "268 kWh/m\u00b2.an",
        "external_id": "5285",
        "external_images_count": 8,
        "external_link": "https://www.athimmo.be/fr/a-louer/ath/appt-1-ch-abbaye-525-\u20ac50-\u20ac-charges-communes--25-\u20ac-provision-eau/5285",
        "external_source": "Athimmo2000Spider",
        "images": [
            "https://i4h6y2e7.stackpathcdn.com/athimmo.public/5285AL.jpg?637374956720240000",
            "https://i4h6y2e7.stackpathcdn.com/athimmo.public/5285BL.jpg?637374956723050000",
            "https://i4h6y2e7.stackpathcdn.com/athimmo.public/5285CL.jpg?637374956636890000",
            "https://i4h6y2e7.stackpathcdn.com/athimmo.public/5285DL.jpg?637374956629750000",
            "https://i4h6y2e7.stackpathcdn.com/athimmo.public/5285EL.jpg?637374956675610000",
            "https://i4h6y2e7.stackpathcdn.com/athimmo.public/5285FL.jpg?637374956633410000",
            "https://i4h6y2e7.stackpathcdn.com/athimmo.public/5285GL.jpg?637374956680350000",
            "https://i4h6y2e7.stackpathcdn.com/athimmo.public/5285HL.jpg?637374956685750000"
        ],
        "landlord_email": "info@athimmo.be",
        "landlord_name": "Athimmo",
        "landlord_phone": "068 28 26 80",
        "latitude": "50.6366800000000000000000000",
        "longitude": "3.7793300000000000000000000",
        "property_type": "apartment",
        "rent": 525,
        "room_count": 1,
        "terrace": true,
        "title": "appt 1 ch abbaye- 525 \u20ac+50 \u20ac charges communes + 25 \u20ac provision eau",
        "zipcode": "7800"
    },
    {
        "address": "Rue Belle Eau 49  7911FRASNES-LEZ-BUISSENAL",
        "bathroom_count": 1,
        "city": "FRASNES-LEZ-BUISSENAL",
        "currency": "EUR",
        "description": "Belle maison 2 fa\u00e7ades 3 chambres avec jardin  PEB D 322 kWh/m\u00b2.an - 20201004007482\r\nComposition :\r\nrez-de-chauss\u00e9e : Hall d'entr\u00e9e (8.07 m\u00b2), salle \u00e0 manger (15.30 m\u00b2), s\u00e9jour (19.56 m\u00b2), pi\u00e8ce interm\u00e9diaire (11.54 m\u00b2), chaufferie (2.64 m\u00b2), buanderie (3.41 m\u00b2), salle de bains (6.60 m\u00b2) - baignoire douche WC lavabo - cuisine \u00e9quip\u00e9e (22.63 m\u00b2) - \u00e9vier double bac taques gaz hotte four frigo lave-vaisselle\r\n\u00c9tage : Hall de distribution (6.38 m\u00b2), 3 chambres (10.72 11.07 et 13.32 m\u00b2), 2 greniers (32 et 35 m\u00b2)\r\nExt\u00e9rieur : Terrasse( 17.33 m\u00b2), jardin , chalet (+/- 12 m\u00b2)\r\nCaract\u00e9ristiques : Chauffage central au gaz + feu au bois dans la cuisine + po\u00eale pellets dans le salon\r\nLoyer 725 \u20ac\r\nLibre imm\u00e9diatement\r\n",
        "energy_label": "322 kWh/m\u00b2.an",
        "external_id": "10100",
        "external_images_count": 15,
        "external_link": "https://www.athimmo.be/fr/a-louer/frasneslezbuissenal/maison-3-chambres-725-\u20ac/10100",
        "external_source": "Athimmo2000Spider",
        "images": [
            "https://i4h6y2e7.stackpathcdn.com/athimmo.public/10100AL.jpg?637374786801860000",
            "https://i4h6y2e7.stackpathcdn.com/athimmo.public/10100BL.jpg?637374786649910000",
            "https://i4h6y2e7.stackpathcdn.com/athimmo.public/10100CL.jpg?637374786654650000",
            "https://i4h6y2e7.stackpathcdn.com/athimmo.public/10100DL.jpg?637376148595330000",
            "https://i4h6y2e7.stackpathcdn.com/athimmo.public/10100EL.jpg?637374786601760000",
            "https://i4h6y2e7.stackpathcdn.com/athimmo.public/10100FL.jpg?637374786610940000",
            "https://i4h6y2e7.stackpathcdn.com/athimmo.public/10100GL.jpg?637374786659130000",
            "https://i4h6y2e7.stackpathcdn.com/athimmo.public/10100HL.jpg?637374786697630000",
            "https://i4h6y2e7.stackpathcdn.com/athimmo.public/10100IL.jpg?637374786736880000",
            "https://i4h6y2e7.stackpathcdn.com/athimmo.public/10100JL.jpg?637374786738610000",
            "https://i4h6y2e7.stackpathcdn.com/athimmo.public/10100KL.jpg?637374786787900000",
            "https://i4h6y2e7.stackpathcdn.com/athimmo.public/10100LL.jpg?637374786742670000",
            "https://i4h6y2e7.stackpathcdn.com/athimmo.public/10100ML.jpg?637374786788650000",
            "https://i4h6y2e7.stackpathcdn.com/athimmo.public/10100NL.jpg?637374786694010000",
            "https://i4h6y2e7.stackpathcdn.com/athimmo.public/10100OL.jpg?637374786702480000"
        ],
        "landlord_email": "info@athimmo.be",
        "landlord_name": "Athimmo",
        "landlord_phone": "068 28 26 80",
        "latitude": "50.6645500000000000000000000",
        "longitude": "3.6219190000000000000000000",
        "property_type": "house",
        "rent": 725,
        "room_count": 3,
        "terrace": false,
        "title": "Maison 3 chambres 725 \u20ac",
        "zipcode": "7911"
    },
    {
        "address": "Rue Isidore Hotton  28 B  7800ATH",
        "available_date": "2020-12-15",
        "bathroom_count": 1,
        "city": "ATH",
        "currency": "EUR",
        "description": "A quelques pas du centre-ville, dans une maison bourgeoise,  beau duplex enti\u00e8rement r\u00e9nov\u00e9 (pas de charges communes) PEB: E (412 kWh/m\u00b2/an) - 20160328013129.\r\nComposition:\r\nSous-sol: cave\r\n1er niveau: bureau, salle \u00e0 manger, cuisine - nouvelle cuisine \u00e9quip\u00e9e - salle de bain - bain, wc, lavabo - WC avec LV\r\n2i\u00e8me niveau: 2 chambres\r\n Loyer: 670 \u20ac ( pas de charges communes)\r\nLibre \u00e0 partir du 15 d\u00e9cembre 2020\r\n\r\n\r\n\r\n",
        "energy_label": "412 kWh/m\u00b2.an",
        "external_id": "6532",
        "external_images_count": 8,
        "external_link": "https://www.athimmo.be/fr/a-louer/ath/duplex-2-chambres-670-\u20ac/6532",
        "external_source": "Athimmo2000Spider",
        "images": [
            "https://i4h6y2e7.stackpathcdn.com/athimmo.public/6532AL.jpg?637371515945720000",
            "https://i4h6y2e7.stackpathcdn.com/athimmo.public/6532BL.jpg?637371516038650000",
            "https://i4h6y2e7.stackpathcdn.com/athimmo.public/6532CL.jpg?637371515924100000",
            "https://i4h6y2e7.stackpathcdn.com/athimmo.public/6532DL.jpg?637371515995720000",
            "https://i4h6y2e7.stackpathcdn.com/athimmo.public/6532EL.jpg?637371515990670000",
            "https://i4h6y2e7.stackpathcdn.com/athimmo.public/6532FL.jpg?637371515988170000",
            "https://i4h6y2e7.stackpathcdn.com/athimmo.public/6532GL.jpg?637371516033700000",
            "https://i4h6y2e7.stackpathcdn.com/athimmo.public/6532HL.jpg?637371515924100000"
        ],
        "landlord_email": "info@athimmo.be",
        "landlord_name": "Athimmo",
        "landlord_phone": "068 28 26 80",
        "latitude": "50.6329512000000000000000000",
        "longitude": "3.7822489000000000000000000",
        "property_type": "apartment",
        "rent": 670,
        "room_count": 2,
        "terrace": false,
        "title": "Duplex 2 chambres 670 \u20ac",
        "zipcode": "7800"
    },
    {
        "address": "Avenue des Sorbiers 14/2  7800ATH",
        "available_date": "2021-01-01",
        "city": "ATH",
        "currency": "EUR",
        "description": "Situ\u00e9 dans l'agr\u00e9able quartier de la Roselle, bel appartement 2 chambres \u00e0 proximit\u00e9 de la Grand Place, de la gare et de tous commerces PEB : B (158 kWh/m\u00b3.an) - 20160724003216.\r\nComposition : \r\nSous-sol : cave (9 m\u00b2), garage privatif (19.5 m\u00b2) et chaufferie.\r\n1er \u00c9tage sans ascenseur : Hall (6.5 m\u00b2), wc, cuisine - \u00e9vier double bacs, taques vitroc\u00e9ramiques, hotte, charbon, four, lave-vaisselle (8 m\u00b2), salon + s\u00e9jour (29 m\u00b2), balcon (4 m\u00b2), salle de bains - douche et simple lavabo (5 m\u00b2) et 2 chambres (16.2 - 21 m\u00b2).\r\nLoyer : 700 \u20ac + 50 \u20ac charges communes + 20 \u20ac pour l'entretien de la chaudi\u00e8re\r\nLibre \u00e0 partir du 1er janvier 2021 ou plus t\u00f4t\r\n\r\n\r\n\r\n\r\n\r\n",
        "elevator": true,
        "energy_label": "158 kWh/m\u00b2.an",
        "external_id": "6746",
        "external_images_count": 7,
        "external_link": "https://www.athimmo.be/fr/a-louer/ath/appt-2-ch--700\u20ac--50\u20ac-charges-communes--20-\u20ac-entretien-chaudiere/6746",
        "external_source": "Athimmo2000Spider",
        "images": [
            "https://i4h6y2e7.stackpathcdn.com/athimmo.public/6746AL.jpg?637371360333840000",
            "https://i4h6y2e7.stackpathcdn.com/athimmo.public/6746BL.jpg?637371360344370000",
            "https://i4h6y2e7.stackpathcdn.com/athimmo.public/6746CL.jpg?637371360331960000",
            "https://i4h6y2e7.stackpathcdn.com/athimmo.public/6746DL.jpg?637371360285040000",
            "https://i4h6y2e7.stackpathcdn.com/athimmo.public/6746EL.jpg?637371360288640000",
            "https://i4h6y2e7.stackpathcdn.com/athimmo.public/6746FL.jpg?637371360378300000",
            "https://i4h6y2e7.stackpathcdn.com/athimmo.public/6746GL.jpg?637371360281160000"
        ],
        "landlord_email": "info@athimmo.be",
        "landlord_name": "Athimmo",
        "landlord_phone": "068 28 26 80",
        "latitude": "50.6339261000000000000000000",
        "longitude": "3.7851641000000000000000000",
        "property_type": "apartment",
        "rent": 700,
        "room_count": 2,
        "terrace": true,
        "title": "Appt 2 ch - 700\u20ac + 50\u20ac charges communes + 20 \u20ac entretien chaudi\u00e8re",
        "zipcode": "7800"
    },
    {
        "address": "Porte de Gand  8/1  7800ATH",
        "available_date": "2020-10-31",
        "bathroom_count": 1,
        "city": "ATH",
        "currency": "EUR",
        "description": "Bel appartement une chambre situ\u00e9 \u00e0 150 m de la Grand Place et \u00e0 30 m de la gare d'Ath.\r\nComposition:\r\nSous-sol : Une cave \r\n2 \u00e8me \u00c9tage : \r\n-S\u00e9jour avec cuisine \u00e9quip\u00e9e  - \u00e9vier double bac, taques vitroc\u00e9ramiques, hotte, four frigo et lave vaisselle\r\n-WC s\u00e9par\u00e9\r\n-Une chambre\r\n-Salle de bains - baignoire et lavabo\r\nLoyer: 570\u20ac + 30\u20ac de charges communes\r\nLibre \u00e0 partir du 1er novembre 2020\r\nPEB C (228 KW/an) 20120912011929",
        "energy_label": "228 kWh/m\u00b2.an",
        "external_id": "10275",
        "external_images_count": 13,
        "external_link": "https://www.athimmo.be/fr/a-louer/ath/appartement-1-chambre-570-\u20ac--30-\u20ac-charges-communes/10275",
        "external_source": "Athimmo2000Spider",
        "images": [
            "https://i4h6y2e7.stackpathcdn.com/athimmo.public/10275AL.jpg?637359324710950000",
            "https://i4h6y2e7.stackpathcdn.com/athimmo.public/10275BL.jpg?637359266195400000",
            "https://i4h6y2e7.stackpathcdn.com/athimmo.public/10275CL.jpg?637359266251610000",
            "https://i4h6y2e7.stackpathcdn.com/athimmo.public/10275DL.jpg?637359266246090000",
            "https://i4h6y2e7.stackpathcdn.com/athimmo.public/10275EL.jpg?637359266239490000",
            "https://i4h6y2e7.stackpathcdn.com/athimmo.public/10275FL.jpg?637359266295290000",
            "https://i4h6y2e7.stackpathcdn.com/athimmo.public/10275GL.jpg?637359266300330000",
            "https://i4h6y2e7.stackpathcdn.com/athimmo.public/10275HL.jpg?637359266192530000",
            "https://i4h6y2e7.stackpathcdn.com/athimmo.public/10275IL.jpg?637359266290890000",
            "https://i4h6y2e7.stackpathcdn.com/athimmo.public/10275JL.jpg?637359266337940000",
            "https://i4h6y2e7.stackpathcdn.com/athimmo.public/10275KL.jpg?637359266345300000",
            "https://i4h6y2e7.stackpathcdn.com/athimmo.public/10275LL.jpg?637359266341550000",
            "https://i4h6y2e7.stackpathcdn.com/athimmo.public/10275ML.jpg?637359266372700000"
        ],
        "landlord_email": "info@athimmo.be",
        "landlord_name": "Athimmo",
        "landlord_phone": "068 28 26 80",
        "latitude": "50.6635200000000000000000000",
        "longitude": "3.7828400000000000000000000",
        "property_type": "apartment",
        "rent": 570,
        "room_count": 1,
        "terrace": false,
        "title": "Appartement 1 chambre 570 \u20ac + 30 \u20ac charges communes",
        "zipcode": "7800"
    },
    {
        "address": "rue Destrebecq 8.2  7971BAS\u00c8CLES",
        "bathroom_count": 1,
        "city": "BAS\u00c8CLES",
        "currency": "EUR",
        "description": "Au centre de Bas\u00e8cles, appartement 2 chambres tr\u00e8s spacieux de +/- 105 m\u00b2  PEB C ( 251kWh/m\u00b2.an) -20130810005656\r\nRez : Hall commun, r\u00e9serve + d\u00e9barras (9 m\u00b2)\r\n1er \u00e9tage : Hall, WC, living + s\u00e9jour (35 m\u00b2), cuisine \u2013 \u00e9vier simple bac, taques vitroc\u00e9ramiques, hotte, four, frigo, emplacement lave-vaisselle dans la buanderie (10 m\u00b2), buanderie (6 m\u00b2), hall de nuit, salle de bains \u2013 baignoire, lavabo (6 m\u00b2), 2 chambres (17 \u2013 16 m\u00b2).\r\nLoyer: 570 \u20ac \r\nLibre Imm\u00e9diatement\r\n\r\n\r\n\r\n",
        "energy_label": "251 kWh/m\u00b2.an",
        "external_id": "4734",
        "external_images_count": 6,
        "external_link": "https://www.athimmo.be/fr/a-louer/basecles/appt-2-ch-tres-spacieux--570\u20ac/4734",
        "external_source": "Athimmo2000Spider",
        "images": [
            "https://i4h6y2e7.stackpathcdn.com/athimmo.public/4734AL.jpg?637358367220490000",
            "https://i4h6y2e7.stackpathcdn.com/athimmo.public/4734BL.jpg?637358367158710000",
            "https://i4h6y2e7.stackpathcdn.com/athimmo.public/4734CL.jpg?637358367165730000",
            "https://i4h6y2e7.stackpathcdn.com/athimmo.public/4734DL.jpg?637358367205080000",
            "https://i4h6y2e7.stackpathcdn.com/athimmo.public/4734EL.jpg?637358367162920000",
            "https://i4h6y2e7.stackpathcdn.com/athimmo.public/4734FL.jpg?637358367205970000"
        ],
        "landlord_email": "info@athimmo.be",
        "landlord_name": "Athimmo",
        "landlord_phone": "068 28 26 80",
        "latitude": "50.5263300000000000000000000",
        "longitude": "3.6510210000000000000000000",
        "property_type": "apartment",
        "rent": 570,
        "room_count": 2,
        "terrace": false,
        "title": "Appt 2 ch tr\u00e8s spacieux  570\u20ac",
        "zipcode": "7971"
    },
    {
        "address": "ruelle des Dominicains 2  7860LESSINES",
        "city": "LESSINES",
        "currency": "EUR",
        "description": "A +/- 50 m de la Grand Place de Lessines et tous commerce, appartement une chambre (r\u00e9nov\u00e9). PEB F (509 kWh/m\u00b2.an) - 20130809004780\r\nComposition\r\n1er \u00e9tage : S\u00e9jour + coin cuisine (30 m\u00b2), 1 chambre \u2013 \u00e9vier simple bac, taques vitroc\u00e9ramiques, hotte, four, frigo (15 m\u00b2), SDD (douche, WC)\r\nLoyer: 475 \u20ac Pas de charges communes\r\nLibre Imm\u00e9diatement\r\n\r\n",
        "energy_label": "509 kWh/m\u00b2.an",
        "external_id": "4873",
        "external_images_count": 6,
        "external_link": "https://www.athimmo.be/fr/a-louer/lessines/appt-1-ch-renove-a-50-m-de-la-grand-place--475-\u20ac/4873",
        "external_source": "Athimmo2000Spider",
        "images": [
            "https://i4h6y2e7.stackpathcdn.com/athimmo.public/4873AL.jpg",
            "https://i4h6y2e7.stackpathcdn.com/athimmo.public/4873BL.jpg",
            "https://i4h6y2e7.stackpathcdn.com/athimmo.public/4873CL.jpg",
            "https://i4h6y2e7.stackpathcdn.com/athimmo.public/4873DL.jpg",
            "https://i4h6y2e7.stackpathcdn.com/athimmo.public/4873EL.jpg",
            "https://i4h6y2e7.stackpathcdn.com/athimmo.public/4873FL.jpg"
        ],
        "landlord_email": "info@athimmo.be",
        "landlord_name": "Athimmo",
        "landlord_phone": "068 28 26 80",
        "latitude": "50.7122264000000000000000000",
        "longitude": "3.8273985000000000000000000",
        "property_type": "apartment",
        "rent": 475,
        "room_count": 1,
        "terrace": false,
        "title": "Appt 1 ch r\u00e9nov\u00e9 \u00e0 50 m de la grand place - 475 \u20ac",
        "zipcode": "7860"
    },
    {
        "address": "rue du Mouton 9/2  7800ATH",
        "available_date": "2020-12-01",
        "bathroom_count": 1,
        "city": "ATH",
        "currency": "EUR",
        "description": "Dans une petite rue calme, \u00e0 100 m de la Grand-Place et 200 m de la gare, appartement 1 chambre au 1er \u00e9tage sans ascenseur.\r\nComposition:\r\n1 er \u00e9tage : Hall d'entr\u00e9e (2,60 m\u00b2), salon (13 m\u00b2), cuisine semi-\u00e9quip\u00e9e - \u00e9vier double bacs, taques au gaz, hotte (17 m\u00b2), salle-de-bains - baignoire, wc, 1 lavabo, emplacement pour machine \u00e0 laver (12 m\u00b2), 1 chambre (13 m\u00b2).\r\nLoyer : 525\u20ac + 25 \u20ac (provisions d'eau)\r\nLibre \u00e0 partir du 1er d\u00e9cembre 2020\r\nPEB D (275 kWh/m\u00b2.an) - 20170427023636\r\n",
        "elevator": true,
        "energy_label": "275 kWh/m\u00b2.an",
        "external_id": "5498",
        "external_images_count": 8,
        "external_link": "https://www.athimmo.be/fr/a-louer/ath/appt-1-ch-en-centre-ville--525\u20ac---25-\u20ac-proveau/5498",
        "external_source": "Athimmo2000Spider",
        "images": [
            "https://i4h6y2e7.stackpathcdn.com/athimmo.public/5498AL.jpg?637375812785450000",
            "https://i4h6y2e7.stackpathcdn.com/athimmo.public/5498BL.jpg?637375812786000000",
            "https://i4h6y2e7.stackpathcdn.com/athimmo.public/5498CL.jpg?637375812658620000",
            "https://i4h6y2e7.stackpathcdn.com/athimmo.public/5498DL.jpg?637375812669720000",
            "https://i4h6y2e7.stackpathcdn.com/athimmo.public/5498EL.jpg?637375812662720000",
            "https://i4h6y2e7.stackpathcdn.com/athimmo.public/5498FL.jpg?637375812727490000",
            "https://i4h6y2e7.stackpathcdn.com/athimmo.public/5498GL.jpg?637375812730670000",
            "https://i4h6y2e7.stackpathcdn.com/athimmo.public/5498HL.jpg?637375812735000000"
        ],
        "landlord_email": "info@athimmo.be",
        "landlord_name": "Athimmo",
        "landlord_phone": "068 28 26 80",
        "latitude": "50.6300100000000000000000000",
        "longitude": "3.7772500000000000000000000",
        "property_type": "apartment",
        "rent": 525,
        "room_count": 1,
        "terrace": false,
        "title": "Appt 1 ch en centre ville - 525\u20ac  + 25 \u20ac prov.eau",
        "zipcode": "7800"
    },
    {
        "address": "Rue de la Candisserie 1/8 1/8  7800ATH",
        "bathroom_count": 1,
        "city": "ATH",
        "currency": "EUR",
        "description": "Bel appartement au deuxi\u00e8me \u00e9tage, neuf, 2 chambres, 2 balcons + emplacement de parking et cave en sous-sol PEB B (104 KW/an) 20170607505846 \r\nDescription :\r\n2 \u00e8me \u00e9tage : Hall d'entr\u00e9e, living avec cuisine \u00e9quip\u00e9e (30.86 m\u00b2) \u00e9vier double bac taques vitroc\u00e9ramiques hotte four frigo cong\u00e9lateur lave-vaisselle , buanderie, WC s\u00e9par\u00e9, salle de douche douche italienne et lavabo, 2 chambres (10.41 et 13 m\u00b2), 2 balcons\r\nSous-sol : cave et emplacement de parking\r\nLoyer : 700 \u20ac + 100 \u20ac pour les charges communes et provision pour l'eau chaude et le chauffage\r\nLibre Imm\u00e9diatement\r\n\r\n\r\n",
        "elevator": true,
        "energy_label": "104 kWh/m\u00b2.an",
        "external_id": "10224",
        "external_images_count": 3,
        "external_link": "https://www.athimmo.be/fr/a-louer/ath/appartement-2-chambres-700-\u20ac/10224",
        "external_source": "Athimmo2000Spider",
        "images": [
            "https://i4h6y2e7.stackpathcdn.com/athimmo.public/10224AL.jpg?637332434401700000",
            "https://i4h6y2e7.stackpathcdn.com/athimmo.public/10224BL.jpg?637332434397440000",
            "https://i4h6y2e7.stackpathcdn.com/athimmo.public/10224CL.jpg?637332434520550000"
        ],
        "landlord_email": "info@athimmo.be",
        "landlord_name": "Athimmo",
        "landlord_phone": "068 28 26 80",
        "latitude": "50.6244799311659000000000000",
        "longitude": "3.7758610181756300000000000",
        "parking": true,
        "property_type": "apartment",
        "rent": 700,
        "room_count": 2,
        "terrace": true,
        "title": "Appartement 2 chambres 700 \u20ac",
        "zipcode": "7800"
    },
    {
        "address": "Abbaye  60/9  7800ATH",
        "available_date": "2020-12-01",
        "bathroom_count": 1,
        "city": "ATH",
        "currency": "EUR",
        "description": "A +/- 600m de la Grand-Place d'Ath et 1,5 km de la Gare PEB B (114 kWh/m\u00b2/an) 20171113016281 \r\nSous-Sol: cave (5m\u00b2)\r\n2\u00e8me \u00e9tage :  Hall+ d\u00e9gagement, W.C., cuisine \u00e9quip\u00e9e (\u00e9vier double bacs - taques vitro - hotte - frigo - cong\u00e9lateur), s\u00e9jour (15m\u00b2), salon (15m\u00b2), 1 chambre (13m\u00b2), salle de bains ( baignoire - lavabo + mobilier), petit balcon (3m\u00b2).\r\nExt\u00e9rieur: Petit balcon (3m\u00b2), parking ext\u00e9rieur privatif (1 place).\r\nLoyer :  600\u20ac + 60\u20ac de charges communes + 20\u20ac de provision pour l'eau.\r\nLibre \u00e0 partir du 1er d\u00e9cembre 2020 ou plus t\u00f4t\r\n",
        "elevator": true,
        "energy_label": "114 kWh/m\u00b2.an",
        "external_id": "8466",
        "external_images_count": 9,
        "external_link": "https://www.athimmo.be/fr/a-louer/ath/appt-1-ch-600-\u20ac--60\u20ac-charges-communes--20-\u20ac-provision-eau/8466",
        "external_source": "Athimmo2000Spider",
        "images": [
            "https://i4h6y2e7.stackpathcdn.com/athimmo.public/8466AL.jpg?637338685327130000",
            "https://i4h6y2e7.stackpathcdn.com/athimmo.public/8466BL.jpg?637338685375460000",
            "https://i4h6y2e7.stackpathcdn.com/athimmo.public/8466CL.jpg?637338685770440000",
            "https://i4h6y2e7.stackpathcdn.com/athimmo.public/8466DL.jpg?637338685739110000",
            "https://i4h6y2e7.stackpathcdn.com/athimmo.public/8466EL.jpg?637338685826280000",
            "https://i4h6y2e7.stackpathcdn.com/athimmo.public/8466FL.jpg?637338686187810000",
            "https://i4h6y2e7.stackpathcdn.com/athimmo.public/8466GL.jpg?637338686217500000",
            "https://i4h6y2e7.stackpathcdn.com/athimmo.public/8466HL.jpg?637338686143780000",
            "https://i4h6y2e7.stackpathcdn.com/athimmo.public/8466IL.jpg?637338685321960000"
        ],
        "landlord_email": "info@athimmo.be",
        "landlord_name": "Athimmo",
        "landlord_phone": "068 28 26 80",
        "latitude": "50.6359500000000000000000000",
        "longitude": "3.7862900000000000000000000",
        "parking": true,
        "property_type": "apartment",
        "rent": 600,
        "room_count": 1,
        "terrace": true,
        "title": "Appt 1 ch 600 \u20ac + 60\u20ac charges communes + 20 \u20ac provision eau",
        "zipcode": "7800"
    },
    {
        "address": "Rue du G\u00e9n\u00e9ral Leman 14/1  7900LEUZE-EN-HAINAUT",
        "city": "LEUZE-EN-HAINAUT",
        "currency": "EUR",
        "description": "Appartement 1 chambre, bien \u00e9quip\u00e9, enti\u00e8rement r\u00e9nov\u00e9, 1\u00e8re location PEB : D (289 kWh/m\u00b2.an) - 20200618022728\r\nComposition :\r\nRez-de-chauss\u00e9e : S\u00e9jour (24.84 m\u00b2), cuisine (11.03 m\u00b2) - \u00e9vier double bac taques gaz hotte four frigo am\u00e9ricain et lave-vaisselle, salle de bains (6.51 m\u00b2) - baignoire WC et lavabo (2), placard (0.83 m\u00b2)\r\nExt\u00e9rieur : courette (5.14 m\u00b2)\r\nCaract\u00e9ristiques : ch\u00e2ssis PVC triple vitrage, feu au gaz\r\nLoyer : 550 \u20ac\r\nLibre Imm\u00e9diatement\r\n\r\n",
        "energy_label": "289 kWh/m\u00b2.an",
        "external_id": "10226",
        "external_images_count": 7,
        "external_link": "https://www.athimmo.be/fr/a-louer/leuzeenhainaut/appartement-1-chambres-550-\u20ac/10226",
        "external_source": "Athimmo2000Spider",
        "images": [
            "https://i4h6y2e7.stackpathcdn.com/athimmo.public/10226AL.jpg?637329237035750000",
            "https://i4h6y2e7.stackpathcdn.com/athimmo.public/10226BL.jpg?637329236629300000",
            "https://i4h6y2e7.stackpathcdn.com/athimmo.public/10226CL.jpg?637329236662470000",
            "https://i4h6y2e7.stackpathcdn.com/athimmo.public/10226DL.jpg?637329236867890000",
            "https://i4h6y2e7.stackpathcdn.com/athimmo.public/10226EL.jpg?637329236893210000",
            "https://i4h6y2e7.stackpathcdn.com/athimmo.public/10226FL.jpg?637329236838090000",
            "https://i4h6y2e7.stackpathcdn.com/athimmo.public/10226GL.jpg?637329236621710000"
        ],
        "landlord_email": "info@athimmo.be",
        "landlord_name": "Athimmo",
        "landlord_phone": "068 28 26 80",
        "latitude": "50.6006300000000000000000000",
        "longitude": "3.6199000000000000000000000",
        "property_type": "apartment",
        "rent": 550,
        "room_count": 1,
        "terrace": false,
        "title": "Appartement 1 chambres 550 \u20ac",
        "zipcode": "7900"
    },
    {
        "address": "Avenue de la Wallonie 22  7900LEUZE-EN-HAINAUT",
        "available_date": "2020-11-01",
        "city": "LEUZE-EN-HAINAUT",
        "currency": "EUR",
        "description": "A la sortie de la ville, \u00e0 5 minutes du centre et de la gare, agr\u00e9able maison 1 chambre avec cour PEB E (370 kWh/m\u00b2.an) - 20120314027558\r\nComposition:\r\nSous-sol : cave (10 m\u00b2)\r\nRez : Hall, salon (16 m\u00b2), s\u00e9jour + cuisine \u2013 \u00e9vier simple bac, taques \u00e9lectriques, hotte, four, emplacement lave-vaisselle (20 m\u00b2), r\u00e9serve, buanderie avec W.C.\r\n\u00c9tage : Hall de nuit, chambre (16 m\u00b2),  dressing,  salle de douche \u2013 douche, wc, lavabo (10 m\u00b2)\r\nExt\u00e9rieur : Cour (10 m\u00b2), remise\r\nLoyer: 550,- \u20ac \r\nLibre \u00e0 partir du 1er novembre 2020\r\n\r\n",
        "energy_label": "370 kWh/m\u00b2.an",
        "external_id": "5171",
        "external_images_count": 7,
        "external_link": "https://www.athimmo.be/fr/a-louer/leuzeenhainaut/a-la-sortie-de-leuze-maison-1ch-avec-cour--550-\u20ac/5171",
        "external_source": "Athimmo2000Spider",
        "images": [
            "https://i4h6y2e7.stackpathcdn.com/athimmo.public/5171AL.jpg?637366150288430000",
            "https://i4h6y2e7.stackpathcdn.com/athimmo.public/5171BL.jpg?637320446713460000",
            "https://i4h6y2e7.stackpathcdn.com/athimmo.public/5171CL.jpg?637320446718700000",
            "https://i4h6y2e7.stackpathcdn.com/athimmo.public/5171DL.jpg?637320446657730000",
            "https://i4h6y2e7.stackpathcdn.com/athimmo.public/5171EL.jpg?637320446668140000",
            "https://i4h6y2e7.stackpathcdn.com/athimmo.public/5171FL.jpg?637320446662970000",
            "https://i4h6y2e7.stackpathcdn.com/athimmo.public/5171GL.jpg?637320446723940000"
        ],
        "landlord_email": "info@athimmo.be",
        "landlord_name": "Athimmo",
        "landlord_phone": "068 28 26 80",
        "latitude": "50.5914622000000000000000000",
        "longitude": "3.6257872000000000000000000",
        "property_type": "house",
        "rent": 550,
        "room_count": 1,
        "terrace": true,
        "title": "A la sortie de Leuze, maison 1ch avec cour - 550 \u20ac",
        "zipcode": "7900"
    },
    {
        "address": "Rue Gaston Destrebecq 8  7971BAS\u00c8CLES",
        "available_date": "2020-11-01",
        "bathroom_count": 1,
        "city": "BAS\u00c8CLES",
        "currency": "EUR",
        "description": "Au centre de Bas\u00e8cles, appartement 3 chambres tr\u00e8s spacieux de +/- 105 m\u00b2 PEB C ( 211kWh/m\u00b2.an) 20130810005529\r\nRez : Hall commun, garage (20 m\u00b2)\r\n1er \u00e9tage : Hall, WC, living + s\u00e9jour (35 m\u00b2), cuisine \u2013 \u00e9vier simple bac, taques vitroc\u00e9ramiques, hotte, four, frigo, emplacement lave-vaisselle dans la buanderie (11 m\u00b2), buanderie (8.5 m\u00b2), hall de nuit, salle de bains \u2013 baignoire, lavabo (5 m\u00b2), 3 chambres (14 - 13 - 12 m\u00b2).\r\nLoyer: 600 \u20ac\r\nLibre \u00e0 partir du 1er novembre 2020\r\n\r\n\r\n\r\n",
        "energy_label": "211 kWh/m\u00b2.an",
        "external_id": "4733",
        "external_images_count": 6,
        "external_link": "https://www.athimmo.be/fr/a-louer/basecles/appt-3-ch-tres-spacieux-600-\u20ac/4733",
        "external_source": "Athimmo2000Spider",
        "images": [
            "https://i4h6y2e7.stackpathcdn.com/athimmo.public/4733AL.jpg?637320425463310000",
            "https://i4h6y2e7.stackpathcdn.com/athimmo.public/4733BL.jpg?637320425178030000",
            "https://i4h6y2e7.stackpathcdn.com/athimmo.public/4733CL.jpg?637320425234830000",
            "https://i4h6y2e7.stackpathcdn.com/athimmo.public/4733DL.jpg?637320425204330000",
            "https://i4h6y2e7.stackpathcdn.com/athimmo.public/4733EL.jpg?637320425394000000",
            "https://i4h6y2e7.stackpathcdn.com/athimmo.public/4733FL.jpg?637320425445180000"
        ],
        "landlord_email": "info@athimmo.be",
        "landlord_name": "Athimmo",
        "landlord_phone": "068 28 26 80",
        "latitude": "50.5263300000000000000000000",
        "longitude": "3.6510200000000000000000000",
        "property_type": "apartment",
        "rent": 600,
        "room_count": 3,
        "terrace": false,
        "title": "Appt 3 ch tr\u00e8s spacieux 600 \u20ac",
        "zipcode": "7971"
    },
    {
        "address": "March\u00e9 au Lin 1 1/1  7800ATH",
        "available_date": "2020-12-01",
        "bathroom_count": 1,
        "city": "ATH",
        "currency": "EUR",
        "description": "Au Centre-Ville \u00e0 +/- 100 m\u00e8tres de la Grand'Place, appartement 2 chambres au 2 \u00e8me \u00c9tage PEB C 180 kWh/m\u00b2.an - 20180704017698\r\n\r\nDescription : \r\n2 \u00e8me \u00c9tage : S\u00e9jour (23 m\u00b2), cuisine (6,80 m\u00b2) - \u00e9vier simple bac, taques vitroc\u00e9ramiques, hotte, four, frigo, cong\u00e9lateur - hall de nuit, buanderie, salle de bains - baignoire et lavabo - W.C. s\u00e9par\u00e9, 2 chambres (14 m\u00b2 et 11 m\u00b2)   \r\nLoyer : 620 \u20ac + 75 \u20ac de charges communes + 40 \u20ac  provision gaz + 30 \u20ac provision eau\r\nLibre \u00e0 partir du 1er d\u00e9cembre 2020 ou plus t\u00f4t\r\n\r\n\r\n",
        "elevator": true,
        "energy_label": "180 kWh/m\u00b2.an",
        "external_id": "8811",
        "external_images_count": 8,
        "external_link": "https://www.athimmo.be/fr/a-louer/ath/appartement-2-chambres-620-\u20ac--75-\u20ac-charges-communes--50-\u20ac-provision/8811",
        "external_source": "Athimmo2000Spider",
        "images": [
            "https://i4h6y2e7.stackpathcdn.com/athimmo.public/8811AL.jpg?637322109491680000",
            "https://i4h6y2e7.stackpathcdn.com/athimmo.public/8811BL.jpg?637316037479380000",
            "https://i4h6y2e7.stackpathcdn.com/athimmo.public/8811CL.jpg?637320451381240000",
            "https://i4h6y2e7.stackpathcdn.com/athimmo.public/8811DL.jpg?637320451386600000",
            "https://i4h6y2e7.stackpathcdn.com/athimmo.public/8811EL.jpg?637320451387150000",
            "https://i4h6y2e7.stackpathcdn.com/athimmo.public/8811FL.jpg?637320451345010000",
            "https://i4h6y2e7.stackpathcdn.com/athimmo.public/8811GL.jpg?637320451344990000",
            "https://i4h6y2e7.stackpathcdn.com/athimmo.public/8811HL.jpg?637320451370190000"
        ],
        "landlord_email": "info@athimmo.be",
        "landlord_name": "Athimmo",
        "landlord_phone": "068 28 26 80",
        "latitude": "50.6302882000000000000000000",
        "longitude": "3.7785264000000000000000000",
        "property_type": "apartment",
        "rent": 620,
        "room_count": 2,
        "terrace": false,
        "title": "Appartement 2 chambres 620 \u20ac + 75 \u20ac charges communes + 50 \u20ac provision gaz + 30 \u20ac provision eau",
        "zipcode": "7800"
    },
    {
        "address": "Rue du Rempart 12/1  7900LEUZE-EN-HAINAUT",
        "available_date": "2020-12-01",
        "bathroom_count": 1,
        "city": "LEUZE-EN-HAINAUT",
        "currency": "EUR",
        "description": "Appartement duplex 2 chambres. A +/- 500m des transports en commun et des commerces PEB D (310 kWh/m\u00b2.an) 20130606004259\r\nDescription : \r\nRez: hall d'entr\u00e9e, d\u00e9barras, living-s\u00e9jour-cuisine am\u00e9ricaine (35m\u00b2)\r\n\u00c9tage: hall de nuit (4m\u00b2), salle de bain (8m\u00b2), WC, 2 chambres (13m\u00b2 et 7,5m\u00b2)\r\nLoyer : 600 \u20ac + 12 \u20ac entretien chaudi\u00e8re \r\nLibre \u00e0 partir du 1er d\u00e9cembre 2020\r\n\r\n",
        "energy_label": "310 kWh/m\u00b2.an",
        "external_id": "1625",
        "external_images_count": 7,
        "external_link": "https://www.athimmo.be/fr/a-louer/leuzeenhainaut/appt-2-ch-en-duplex--600-\u20ac--12-\u20ac-entretien-chaudiere/1625",
        "external_source": "Athimmo2000Spider",
        "images": [
            "https://i4h6y2e7.stackpathcdn.com/athimmo.public/1625AL.jpg?637311748243630000",
            "https://i4h6y2e7.stackpathcdn.com/athimmo.public/1625BL.jpg?637311748178880000",
            "https://i4h6y2e7.stackpathcdn.com/athimmo.public/1625CL.jpg?637311748176840000",
            "https://i4h6y2e7.stackpathcdn.com/athimmo.public/1625DL.jpg?637311748341680000",
            "https://i4h6y2e7.stackpathcdn.com/athimmo.public/1625EL.jpg?637311748361840000",
            "https://i4h6y2e7.stackpathcdn.com/athimmo.public/1625FL.jpg?637311748341750000",
            "https://i4h6y2e7.stackpathcdn.com/athimmo.public/1625GL.jpg?637311748472780000"
        ],
        "landlord_email": "info@athimmo.be",
        "landlord_name": "Athimmo",
        "landlord_phone": "068 28 26 80",
        "latitude": "50.5991100000000000000000000",
        "longitude": "3.6216100000000000000000000",
        "property_type": "apartment",
        "rent": 600,
        "room_count": 2,
        "terrace": false,
        "title": "Appt 2 ch en duplex - 600 \u20ac + 12 \u20ac entretien chaudi\u00e8re",
        "zipcode": "7900"
    },
    {
        "address": "rue des Fr\u00e8res Descamps 48  7800ATH",
        "available_date": "2020-09-01",
        "city": "ATH",
        "currency": "EUR",
        "description": "Proche de la gare et du centre ville, chambre d'\u00e9tudiant \u00e0 louer (rez de chauss\u00e9e) PEB E 382 kWh/m\u00b2.an - 20150519005074\r\n",
        "energy_label": "382 kWh/m\u00b2.an",
        "external_id": "4335",
        "external_images_count": 1,
        "external_link": "https://www.athimmo.be/fr/a-louer/ath/chambre-detudiant-proche-de-la-gare/4335",
        "external_source": "Athimmo2000Spider",
        "images": [
            "https://i4h6y2e7.stackpathcdn.com/athimmo.public/4335AL.jpg?637284151644450000"
        ],
        "landlord_email": "info@athimmo.be",
        "landlord_name": "Athimmo",
        "landlord_phone": "068 28 26 80",
        "latitude": "50.6276430000000000000000000",
        "longitude": "3.7756385000000000000000000",
        "property_type": "apartment",
        "rent": 300,
        "room_count": 1,
        "terrace": false,
        "title": "Chambre d'\u00e9tudiant, proche de la gare",
        "zipcode": "7800"
    },
    {
        "address": "rue Ernest Cambier 33/2  7800ATH",
        "available_date": "2020-09-01",
        "city": "ATH",
        "currency": "EUR",
        "description": "Situ\u00e9 en plein centre-ville, \u00e0 20m de la Grand Place et \u00e0 50m de la Gare, superbe appartement 1 chambre enti\u00e8rement r\u00e9nov\u00e9  PEB G (894 KW/an) 20120312020763\r\nDescription:\r\n2\u00e8me \u00e9tage: s\u00e9jour (24 m\u00b2), cuisine \u00e9quip\u00e9e \u00e9vier simple - taques \u00e9lectriques - hotte - four - frigo - emplacement lave-vaisselle (10 m\u00b2), 1 chambre (15 m\u00b2), SDD douche - lavabo, WC, placard sur le palier, couloir\r\nLoyer: 600\u20ac + 20 \u20ac charges communes\r\nLibre \u00e0 partir du 1er septembre 2020\r\n\r\n",
        "energy_label": "894 kWh/m\u00b2.an",
        "external_id": "6106",
        "external_images_count": 7,
        "external_link": "https://www.athimmo.be/fr/a-louer/ath/appartement-1-chambre-600\u20ac--20-\u20ac-charges-communes/6106",
        "external_source": "Athimmo2000Spider",
        "images": [
            "https://i4h6y2e7.stackpathcdn.com/athimmo.public/6106AL.jpg?637268598617060000",
            "https://i4h6y2e7.stackpathcdn.com/athimmo.public/6106BL.jpg?637268598561750000",
            "https://i4h6y2e7.stackpathcdn.com/athimmo.public/6106CL.jpg?637268598491380000",
            "https://i4h6y2e7.stackpathcdn.com/athimmo.public/6106DL.jpg?637268598478790000",
            "https://i4h6y2e7.stackpathcdn.com/athimmo.public/6106EL.jpg?637268598498360000",
            "https://i4h6y2e7.stackpathcdn.com/athimmo.public/6106FL.jpg?637268598556010000",
            "https://i4h6y2e7.stackpathcdn.com/athimmo.public/6106GL.jpg?637268598568900000"
        ],
        "landlord_email": "info@athimmo.be",
        "landlord_name": "Athimmo",
        "landlord_phone": "068 28 26 80",
        "latitude": "50.6290600000000000000000000",
        "longitude": "3.7769490000000000000000000",
        "property_type": "apartment",
        "rent": 600,
        "room_count": 1,
        "terrace": false,
        "title": "Appartement 1 chambre 600\u20ac + 20 \u20ac charges communes",
        "zipcode": "7800"
    },
    {
        "address": "Rue du Coll\u00e8ge 12  7800ATH",
        "available_date": "2020-07-01",
        "bathroom_count": 2,
        "city": "ATH",
        "currency": "EUR",
        "description": "Appartement 2 chambres (triplex) en Centre Ville  PEB E (393 kWh/m\u00b2.an) - 20120829014085\r\nComposition :\r\nRez-de-chauss\u00e9e : hall d'entr\u00e9e (5 m\u00b2)\r\n1er \u00e9tage : cuisine (13.50 m\u00b2) - \u00e9vier simple bac taques vitroc\u00e9ramiques hotte four frigo lave-vaisselle - salon (20.82 m\u00b2), buanderie (2 m\u00b2)\r\n2 \u00e8me \u00e9tage : Hall (4.30 m\u00b2), WC s\u00e9par\u00e9 (1.86 m\u00b2), une chambre (19.02 m\u00b2), salle de bains (6.53 m\u00b2)  bain et lavabo\r\n3 \u00e8me \u00e9tage : une chambre (18.40 m\u00b2) + d\u00e9barras (5 m\u00b2), salle de bains (5.21 m\u00b2)  lavabo baignoire WC\r\nLoyer : 775 \u20ac\r\nLibre \u00e0 partir du 1er juillet 2020\r\n",
        "energy_label": "393 kWh/m\u00b2.an",
        "external_id": "10073",
        "external_images_count": 10,
        "external_link": "https://www.athimmo.be/fr/a-louer/ath/appartement-2-chambres-775-\u20ac/10073",
        "external_source": "Athimmo2000Spider",
        "images": [
            "https://i4h6y2e7.stackpathcdn.com/athimmo.public/10073AL.jpg",
            "https://i4h6y2e7.stackpathcdn.com/athimmo.public/10073BL.jpg",
            "https://i4h6y2e7.stackpathcdn.com/athimmo.public/10073CL.jpg",
            "https://i4h6y2e7.stackpathcdn.com/athimmo.public/10073DL.jpg",
            "https://i4h6y2e7.stackpathcdn.com/athimmo.public/10073EL.jpg",
            "https://i4h6y2e7.stackpathcdn.com/athimmo.public/10073FL.jpg",
            "https://i4h6y2e7.stackpathcdn.com/athimmo.public/10073GL.jpg",
            "https://i4h6y2e7.stackpathcdn.com/athimmo.public/10073HL.jpg",
            "https://i4h6y2e7.stackpathcdn.com/athimmo.public/10073IL.jpg",
            "https://i4h6y2e7.stackpathcdn.com/athimmo.public/10073JL.jpg?637359231763250000"
        ],
        "landlord_email": "info@athimmo.be",
        "landlord_name": "Athimmo",
        "landlord_phone": "068 28 26 80",
        "latitude": "50.6289200000000000000000000",
        "longitude": "3.7771380000000000000000000",
        "property_type": "apartment",
        "rent": 775,
        "room_count": 2,
        "terrace": false,
        "title": "Appartement 2 chambres 775 \u20ac",
        "zipcode": "7800"
    },
    {
        "address": "du Rempart  12/2  7900LEUZE-EN-HAINAUT",
        "available_date": "2020-10-01",
        "bathroom_count": 1,
        "city": "LEUZE-EN-HAINAUT",
        "currency": "EUR",
        "description": "A +/- 500m des transports en commun et des commerces, appartement duplex 2 chambres PEB D (294 kWh/m\u00b2.an) - 20130107000364\r\nComposition : \r\nRez: hall d'entr\u00e9e, d\u00e9barras, living-s\u00e9jour-cuisine am\u00e9ricaine (35m\u00b2)\r\n\u00c9tage: hall de nuit (4m\u00b2), salle de bain (8m\u00b2), WC, 2 chambres (13m\u00b2 et 7,5m\u00b2)\r\nLoyer : 640 \u20ac + 12 \u20ac de l'entretien de la chaudi\u00e8re \r\nLibre \u00e0 partir du 1er octobre 2020\r\n\r\n\r\n",
        "energy_label": "294 kWh/m\u00b2.an",
        "external_id": "2824",
        "external_images_count": 5,
        "external_link": "https://www.athimmo.be/fr/a-louer/leuzeenhainaut/appt-2-chambres-en-duplex-640-\u20ac--12-\u20ac-entretien-chaudiere/2824",
        "external_source": "Athimmo2000Spider",
        "images": [
            "https://i4h6y2e7.stackpathcdn.com/athimmo.public/2824AL.jpg",
            "https://i4h6y2e7.stackpathcdn.com/athimmo.public/2824BL.jpg",
            "https://i4h6y2e7.stackpathcdn.com/athimmo.public/2824CL.jpg",
            "https://i4h6y2e7.stackpathcdn.com/athimmo.public/2824DL.jpg",
            "https://i4h6y2e7.stackpathcdn.com/athimmo.public/2824EL.jpg"
        ],
        "landlord_email": "info@athimmo.be",
        "landlord_name": "Athimmo",
        "landlord_phone": "068 28 26 80",
        "latitude": "50.5991100000000000000000000",
        "longitude": "3.6216100000000000000000000",
        "property_type": "apartment",
        "rent": 640,
        "room_count": 2,
        "terrace": false,
        "title": "Appt 2 chambres en duplex -640 \u20ac + 12 \u20ac entretien chaudi\u00e8re",
        "zipcode": "7900"
    },
    {
        "address": "Rue Haute 10 BTE 3  7800ATH",
        "available_date": "2020-05-12",
        "bathroom_count": 1,
        "city": "ATH",
        "currency": "EUR",
        "description": "Situ\u00e9 au coeur de la ville, \u00e0 100 m de la Grand Place et 300 m de la gare, en face de la poste, bel appartement, tr\u00e8s lumineux, au 2e \u00e9tage sans ascenseur\r\n\r\nDescription : \r\n\r\n2e \u00e9tage : Living, cuisine semi-\u00e9quip\u00e9e -\u00e9vier, taques \u00e9lectriques, hotte, four, 1 chambre, hall, salle-de-bains, W.C., \r\n\r\nLoyer : 590\u20ac\r\nLibre Imm\u00e9diatement\r\n\r\n\r\n",
        "elevator": true,
        "energy_label": "265 kWh/m\u00b2.an",
        "external_id": "1830",
        "external_images_count": 11,
        "external_link": "https://www.athimmo.be/fr/a-louer/ath/appartement--590\u20ac--pas-de-chcomm/1830",
        "external_source": "Athimmo2000Spider",
        "images": [
            "https://i4h6y2e7.stackpathcdn.com/athimmo.public/1830AL.jpg?637338717786370000",
            "https://i4h6y2e7.stackpathcdn.com/athimmo.public/1830BL.jpg",
            "https://i4h6y2e7.stackpathcdn.com/athimmo.public/1830CL.jpg",
            "https://i4h6y2e7.stackpathcdn.com/athimmo.public/1830DL.jpg",
            "https://i4h6y2e7.stackpathcdn.com/athimmo.public/1830EL.jpg",
            "https://i4h6y2e7.stackpathcdn.com/athimmo.public/1830FL.jpg",
            "https://i4h6y2e7.stackpathcdn.com/athimmo.public/1830GL.jpg",
            "https://i4h6y2e7.stackpathcdn.com/athimmo.public/1830HL.jpg",
            "https://i4h6y2e7.stackpathcdn.com/athimmo.public/1830IL.jpg",
            "https://i4h6y2e7.stackpathcdn.com/athimmo.public/1830JL.jpg",
            "https://i4h6y2e7.stackpathcdn.com/athimmo.public/1830KL.jpg"
        ],
        "landlord_email": "info@athimmo.be",
        "landlord_name": "Athimmo",
        "landlord_phone": "068 28 26 80",
        "latitude": "50.6335009000000000000000000",
        "longitude": "3.7882733000000000000000000",
        "property_type": "apartment",
        "rent": 590,
        "room_count": 1,
        "terrace": false,
        "title": "appartement - 590\u20ac - pas de ch.comm",
        "zipcode": "7800"
    },
    {
        "address": "Rue des Fr\u00e8res Gilbert 14/1  7800ATH",
        "city": "ATH",
        "currency": "EUR",
        "description": "Dans un immeuble du centre historique d'Ath, superbe appartement style loft - brique et beton, au rez-de-chauss\u00e9e. PEB C (186kWh/m\u00b2.an) - 20151013024390\r\nSitu\u00e9 en plein centre ville, \u00e0 2 pas de la gare et de la grand Place.\r\nDescription :\r\nRez-de-chauss\u00e9e : Cuisine (15 m\u00b2), s\u00e9jour (20 m\u00b2), W.C., hall de nuit, salle de douches, 1 chambre (11 m\u00b2)\r\nExt\u00e9rieur: cour int\u00e9rieure (7 m\u00b2), cour ext\u00e9rieure (15 m\u00b2).\r\nLoyer : 565\u20ac + 15\u20ac charges communes\r\nLibre Imm\u00e9diatement\r\n",
        "energy_label": "186 kWh/m\u00b2.an",
        "external_id": "4194",
        "external_images_count": 10,
        "external_link": "https://www.athimmo.be/fr/a-louer/ath/appt-neuf--style-loft--brique-et-beton-avec-cour--565\u20ac--15-\u20ac-charg/4194",
        "external_source": "Athimmo2000Spider",
        "images": [
            "https://i4h6y2e7.stackpathcdn.com/athimmo.public/4194AL.jpg",
            "https://i4h6y2e7.stackpathcdn.com/athimmo.public/4194BL.jpg",
            "https://i4h6y2e7.stackpathcdn.com/athimmo.public/4194CL.jpg",
            "https://i4h6y2e7.stackpathcdn.com/athimmo.public/4194DL.jpg",
            "https://i4h6y2e7.stackpathcdn.com/athimmo.public/4194EL.jpg",
            "https://i4h6y2e7.stackpathcdn.com/athimmo.public/4194FL.jpg",
            "https://i4h6y2e7.stackpathcdn.com/athimmo.public/4194GL.jpg",
            "https://i4h6y2e7.stackpathcdn.com/athimmo.public/4194HL.jpg",
            "https://i4h6y2e7.stackpathcdn.com/athimmo.public/4194IL.jpg",
            "https://i4h6y2e7.stackpathcdn.com/athimmo.public/4194JL.jpg"
        ],
        "landlord_email": "info@athimmo.be",
        "landlord_name": "Athimmo",
        "landlord_phone": "068 28 26 80",
        "latitude": "50.6294300000000000000000000",
        "longitude": "3.7774890000000000000000000",
        "property_type": "apartment",
        "rent": 565,
        "room_count": 1,
        "terrace": true,
        "title": "Appt NEUF - style loft - brique et b\u00e9ton avec cour - 565\u20ac + 15 \u20ac charges communes",
        "zipcode": "7800"
    },
    {
        "address": "IMPASSE LORETTE  7/9  7800ATH",
        "available_date": "2020-10-17",
        "city": "ATH",
        "currency": "EUR",
        "description": "Situ\u00e9 dans une impasse, proche du centre-ville et de nombreux commerces, agr\u00e9able appartement situ\u00e9 au 1er \u00e9tage, 2 chambres avec balcon et ascenseur PEB B (116 KW/an) 20150617003013\r\nDescription:\r\nSous-sol: cave (C5) et emplacement de parking\r\n1er \u00e9tage: hall d'entr\u00e9e, WC, cuisine \u00e9quip\u00e9e (8 m\u00b2) \u00e9vier doubles bacs - taques vitro - hotte - four ouverte sur le s\u00e9jour (30 m\u00b2), hall de nuit, SDD douche - lavabo (5 m\u00b2), 2 chambres (11 et 8 m\u00b2), buanderie \r\nExt\u00e9rieur: Balcon (5 m\u00b2)\r\nLoyer: 650 \u20ac + 60 \u20ac charges communes\r\nLibre \u00e0 partir du 17 octobre 2020\r\n\r\n",
        "elevator": true,
        "energy_label": "116 kWh/m\u00b2.an",
        "external_id": "4105",
        "external_images_count": 16,
        "external_link": "https://www.athimmo.be/fr/a-louer/ath/appartement-2-ch-avec-terrasse-cave-parking--650-\u20ac--60\u20ac-charges-c/4105",
        "external_source": "Athimmo2000Spider",
        "images": [
            "https://i4h6y2e7.stackpathcdn.com/athimmo.public/4105AL.jpg?637303282653230000",
            "https://i4h6y2e7.stackpathcdn.com/athimmo.public/4105BL.jpg?637303282981650000",
            "https://i4h6y2e7.stackpathcdn.com/athimmo.public/4105CL.jpg?637303282980940000",
            "https://i4h6y2e7.stackpathcdn.com/athimmo.public/4105DL.jpg?637303282942740000",
            "https://i4h6y2e7.stackpathcdn.com/athimmo.public/4105EL.jpg?637303282648830000",
            "https://i4h6y2e7.stackpathcdn.com/athimmo.public/4105FL.jpg?637303282648990000",
            "https://i4h6y2e7.stackpathcdn.com/athimmo.public/4105GL.jpg?637303282702970000",
            "https://i4h6y2e7.stackpathcdn.com/athimmo.public/4105HL.jpg?637303282705060000",
            "https://i4h6y2e7.stackpathcdn.com/athimmo.public/4105IL.jpg?637303282709300000",
            "https://i4h6y2e7.stackpathcdn.com/athimmo.public/4105JL.jpg?637303282755890000",
            "https://i4h6y2e7.stackpathcdn.com/athimmo.public/4105KL.jpg?637303282753430000",
            "https://i4h6y2e7.stackpathcdn.com/athimmo.public/4105LL.jpg?637303282761130000",
            "https://i4h6y2e7.stackpathcdn.com/athimmo.public/4105ML.jpg?637303282802640000",
            "https://i4h6y2e7.stackpathcdn.com/athimmo.public/4105NL.jpg?637303282822320000",
            "https://i4h6y2e7.stackpathcdn.com/athimmo.public/4105OL.jpg?637303282815350000",
            "https://i4h6y2e7.stackpathcdn.com/athimmo.public/4105PL.jpg?637303282872740000"
        ],
        "landlord_email": "info@athimmo.be",
        "landlord_name": "Athimmo",
        "landlord_phone": "068 28 26 80",
        "latitude": "50.6360200000000000000000000",
        "longitude": "3.7922570000000000000000000",
        "parking": true,
        "property_type": "apartment",
        "rent": 650,
        "room_count": 2,
        "terrace": true,
        "title": "appartement 2 ch. avec terrasse, cave, parking - 650 \u20ac + 60\u20ac charges communes",
        "zipcode": "7800"
    },
    {
        "address": "Square de la Philharmonique  9/6  7800ATH",
        "available_date": "2021-01-01",
        "city": "ATH",
        "currency": "EUR",
        "description": "Bel appartement 2 chambres au premier \u00e9tage avec cave et emplacement de parking en sous-sol PEB A (61 kWh/m\u00b2.an) - 20190930504233\r\nComposition :\r\n1er \u00e9tage : Hall d'entr\u00e9e, buanderie / local technique, WC s\u00e9par\u00e9, cuisine ouverte sur un grand living tr\u00e8s lumineux - \u00e9vier simple bac taques vitroc\u00e9ramiques hotte four frigo cong\u00e9lateur lave-vaisselle - hall de nuit , salle de bains avec espace de rangement, 2 chambres , grande terrasse\r\nSous-sol : emplacement de parking + cave\r\nLoyer : 700 \u20ac + 90 \u20ac charges communes\r\nLibre \u00e0 partir du 1er janvier 2021\r\n\r\n\r\n\r\n\r\n",
        "elevator": true,
        "energy_label": "61 kWh/m\u00b2.an",
        "external_id": "9627",
        "external_images_count": 8,
        "external_link": "https://www.athimmo.be/fr/a-louer/ath/appartement-2-chambres-700-\u20ac--90-\u20ac-charges-communes/9627",
        "external_source": "Athimmo2000Spider",
        "images": [
            "https://i4h6y2e7.stackpathcdn.com/athimmo.public/9627AL.jpg?637369778791070000",
            "https://i4h6y2e7.stackpathcdn.com/athimmo.public/9627BL.jpg?637369778653820000",
            "https://i4h6y2e7.stackpathcdn.com/athimmo.public/9627CL.jpg?637369778672270000",
            "https://i4h6y2e7.stackpathcdn.com/athimmo.public/9627DL.jpg?637369778725040000",
            "https://i4h6y2e7.stackpathcdn.com/athimmo.public/9627EL.jpg?637369778725960000",
            "https://i4h6y2e7.stackpathcdn.com/athimmo.public/9627FL.jpg?637369778791060000",
            "https://i4h6y2e7.stackpathcdn.com/athimmo.public/9627GL.jpg?637369778735470000",
            "https://i4h6y2e7.stackpathcdn.com/athimmo.public/9627HL.jpg?637369778663040000"
        ],
        "landlord_email": "info@athimmo.be",
        "landlord_name": "Athimmo",
        "landlord_phone": "068 28 26 80",
        "latitude": "50.6340400000000000000000000",
        "longitude": "3.7819690000000000000000000",
        "parking": true,
        "property_type": "apartment",
        "rent": 700,
        "room_count": 2,
        "terrace": true,
        "title": "Appartement 2 chambres 700 \u20ac + 90 \u20ac charges communes",
        "zipcode": "7800"
    },
    {
        "address": "Rue de Grammont 2/2 2/2  7830BASSILLY",
        "available_date": "2020-12-22",
        "bathroom_count": 1,
        "city": "BASSILLY",
        "currency": "EUR",
        "description": " Id\u00e9alement situ\u00e9 non loin d\u2019un acc\u00e8s E429 et proche du centre de Bassilly, appartement deux chambres de 70 m\u00b2 au 1er \u00e9tage PEB E 390 kWh/m\u00b2.an - 20150109021610\r\nComposition:\r\n1er \u00c9tage : Hall, s\u00e9jour (20 m\u00b2), cuisine \u2013 \u00e9vier double bacs, taques \u00e9lectriques, hotte, four, frigo, salle-de-bains (5 m\u00b2) \u2013 baignoire, wc, lavabo, hall de nuit (5 m\u00b2), 2 chambres (14 \u2013 17.20 m\u00b2), d\u00e9barras.\r\nExt\u00e9rieur\u00a0: balcon + garage\r\nLoyer : 600 \u20ac + 15 \u20ac entretien des parties ext\u00e9rieures communes\r\nLibre \u00e0 partir du 22 d\u00e9cembre 2020\r\n\r\n",
        "energy_label": "390 kWh/m\u00b2.an",
        "external_id": "2896",
        "external_images_count": 10,
        "external_link": "https://www.athimmo.be/fr/a-louer/bassilly/idealement-situe-appt-2-ch600\u20ac---15-\u20ac-entretien-jardin/2896",
        "external_source": "Athimmo2000Spider",
        "images": [
            "https://i4h6y2e7.stackpathcdn.com/athimmo.public/2896AL.jpg",
            "https://i4h6y2e7.stackpathcdn.com/athimmo.public/2896BL.jpg",
            "https://i4h6y2e7.stackpathcdn.com/athimmo.public/2896CL.jpg",
            "https://i4h6y2e7.stackpathcdn.com/athimmo.public/2896DL.jpg",
            "https://i4h6y2e7.stackpathcdn.com/athimmo.public/2896EL.jpg",
            "https://i4h6y2e7.stackpathcdn.com/athimmo.public/2896FL.jpg",
            "https://i4h6y2e7.stackpathcdn.com/athimmo.public/2896GL.jpg",
            "https://i4h6y2e7.stackpathcdn.com/athimmo.public/2896HL.jpg",
            "https://i4h6y2e7.stackpathcdn.com/athimmo.public/2896IL.jpg",
            "https://i4h6y2e7.stackpathcdn.com/athimmo.public/2896JL.jpg"
        ],
        "landlord_email": "info@athimmo.be",
        "landlord_name": "Athimmo",
        "landlord_phone": "068 28 26 80",
        "latitude": "50.6801300000000000000000000",
        "longitude": "3.9319200000000000000000000",
        "property_type": "apartment",
        "rent": 600,
        "room_count": 2,
        "terrace": true,
        "title": "Id\u00e9alement situ\u00e9, appt 2 ch-600\u20ac  + 15 \u20ac entretien jardin",
        "zipcode": "7830"
    },
    {
        "address": "Rue Saint-Martin 69  7941ATTRE",
        "bathroom_count": 1,
        "city": "ATTRE",
        "currency": "EUR",
        "description": "Agr\u00e9able petite maison 1 chambre avec garage \u00e0 300m de la gare, \u00e0 +/- 7km du centre d'Ath et \u00e0 +/- 5km du centre de Chi\u00e8vres PEB G (555 kWh/m\u00b2.an - 20150226009455)\r\n\r\nDescription:\r\nRez: hall (6 m\u00b2), s\u00e9jour avec coin nouvelle cuisine(21 m\u00b2), salon (12 m\u00b2), salle de bains -1 lavabo - baignoire - WC (5 m\u00b2)\r\n\u00c9tage: hall de nuit (9 m\u00b2), 1 chambre (19 m\u00b2)\r\nExt\u00e9rieur: garage\r\nLoyer: 570 \u20ac (entretien de la pelouse et des haies compris)\r\nLibre Imm\u00e9diatement\r\n\r\n\r\n\r\n\r\n",
        "energy_label": "555 kWh/m\u00b2.an",
        "external_id": "5657",
        "external_images_count": 9,
        "external_link": "https://www.athimmo.be/fr/a-louer/attre/petite-maison-1-chambre-avec-garage-570-\u20ac/5657",
        "external_source": "Athimmo2000Spider",
        "images": [
            "https://i4h6y2e7.stackpathcdn.com/athimmo.public/5657AL.jpg?637357506071960000",
            "https://i4h6y2e7.stackpathcdn.com/athimmo.public/5657BL.jpg",
            "https://i4h6y2e7.stackpathcdn.com/athimmo.public/5657CL.jpg",
            "https://i4h6y2e7.stackpathcdn.com/athimmo.public/5657DL.jpg",
            "https://i4h6y2e7.stackpathcdn.com/athimmo.public/5657EL.jpg",
            "https://i4h6y2e7.stackpathcdn.com/athimmo.public/5657FL.jpg",
            "https://i4h6y2e7.stackpathcdn.com/athimmo.public/5657GL.jpg",
            "https://i4h6y2e7.stackpathcdn.com/athimmo.public/5657HL.jpg",
            "https://i4h6y2e7.stackpathcdn.com/athimmo.public/5657IL.jpg"
        ],
        "landlord_email": "info@athimmo.be",
        "landlord_name": "Athimmo",
        "landlord_phone": "068 28 26 80",
        "latitude": "50.6068934000000000000000000",
        "longitude": "3.8386196000000000000000000",
        "property_type": "house",
        "rent": 570,
        "room_count": 1,
        "terrace": false,
        "title": "petite maison 1 chambre avec garage 570 \u20ac",
        "zipcode": "7941"
    },
    {
        "address": " Ernest Cambier 26/2  7800ATH",
        "available_date": "2020-10-25",
        "bathroom_count": 1,
        "city": "ATH",
        "currency": "EUR",
        "description": "Bel appartement duplex au 2 \u00e8me \u00e9tage; id\u00e9alement situ\u00e9 au coeur de la ville, \u00e0 50 m de la Grand Place et 150 m de la gare.  PEB C (205 kWh/m\u00b2.an) - 20180614015671\r\nDescription : \r\n2 \u00e8me \u00c9tage : Living avec coin cuisine ( 38 m\u00b2) - \u00e9vier simple bacs taques \u00e9lectriques hotte four frigo - buanderie, salle de bains - baignoire lavabo W.C. - deux chambres + dressing (15 et 23 m\u00b2) ,  bureau (30 m\u00b2) \r\nLoyer : 690 \u20ac\r\nLibre \u00e0 partir du 25 octobre 2020\r\n PEB C (205 kWh/m\u00b2.an) - 20180614015671\r\n",
        "energy_label": "205 kWh/m\u00b2.an",
        "external_id": "8801",
        "external_images_count": 13,
        "external_link": "https://www.athimmo.be/fr/a-louer/ath/appart-duplex-2-chambres/8801",
        "external_source": "Athimmo2000Spider",
        "images": [
            "https://i4h6y2e7.stackpathcdn.com/athimmo.public/8801AL.jpg?637280790587990000",
            "https://i4h6y2e7.stackpathcdn.com/athimmo.public/8801BL.jpg?637280790371080000",
            "https://i4h6y2e7.stackpathcdn.com/athimmo.public/8801CL.jpg?637280790437460000",
            "https://i4h6y2e7.stackpathcdn.com/athimmo.public/8801DL.jpg?637280790443360000",
            "https://i4h6y2e7.stackpathcdn.com/athimmo.public/8801EL.jpg?637280790365440000",
            "https://i4h6y2e7.stackpathcdn.com/athimmo.public/8801FL.jpg?637280790241190000",
            "https://i4h6y2e7.stackpathcdn.com/athimmo.public/8801GL.jpg?637280790432290000",
            "https://i4h6y2e7.stackpathcdn.com/athimmo.public/8801HL.jpg?637280790511790000",
            "https://i4h6y2e7.stackpathcdn.com/athimmo.public/8801IL.jpg?637280790513720000",
            "https://i4h6y2e7.stackpathcdn.com/athimmo.public/8801JL.jpg?637280790533350000",
            "https://i4h6y2e7.stackpathcdn.com/athimmo.public/8801KL.jpg?637280790587150000",
            "https://i4h6y2e7.stackpathcdn.com/athimmo.public/8801LL.jpg?637280790381650000",
            "https://i4h6y2e7.stackpathcdn.com/athimmo.public/8801ML.jpg?637280790219500000"
        ],
        "landlord_email": "info@athimmo.be",
        "landlord_name": "Athimmo",
        "landlord_phone": "068 28 26 80",
        "latitude": "50.6288691000000000000000000",
        "longitude": "3.7768812000000000000000000",
        "property_type": "apartment",
        "rent": 690,
        "room_count": 2,
        "terrace": false,
        "title": "Appart duplex 2 chambres",
        "zipcode": "7800"
    },
    {
        "address": "Square de la Demi Lune 4 Bte 8 4/8  7800ATH",
        "available_date": "2021-01-01",
        "bathroom_count": 1,
        "city": "ATH",
        "currency": "EUR",
        "description": "Appartement 2 chambres, neuf, spacieux, lumineux avec une belle terrasse PEB A 62 kWh/m\u00b2.an - 20171222509085\r\nDescription : \r\n1 er \u00e9tage : Hall d'entr\u00e9e (4.85 m\u00b2), s\u00e9jour (29 m\u00b2), cuisine (4.10 m\u00b2) - \u00e9vier double bac taques vitroc\u00e9ramiques hotte (charbon) four frigo lave-vaisselle - hall de nuit (5 m\u00b2), WC s\u00e9par\u00e9, salle de bains - baignoire lavabos + mobilier -\r\n2 chambres (12.95 m\u00b2 et 10.52 m\u00b2).  \r\nExt\u00e9rieur : Terrasse (11 m\u00b2) ,  1 emplacement de parking int\u00e9rieur\r\nSous-sol : cave + parking v\u00e9lo\r\nLoyer : 725 \u20ac + 80\u20ac  charges communes + 60\u20ac provisions eau chaude et chauffage \r\nLibre \u00e0 partir du 1er janvier 2021\r\n\r\n\r\n",
        "elevator": true,
        "energy_label": "62 kWh/m\u00b2.an",
        "external_id": "9472",
        "external_images_count": 10,
        "external_link": "https://www.athimmo.be/fr/a-louer/ath/appartement-2-chambres-725-\u20ac--80-\u20ac-charges-communes--60-\u20ac-provisions/9472",
        "external_source": "Athimmo2000Spider",
        "images": [
            "https://i4h6y2e7.stackpathcdn.com/athimmo.public/9472AL.jpg",
            "https://i4h6y2e7.stackpathcdn.com/athimmo.public/9472BL.jpg",
            "https://i4h6y2e7.stackpathcdn.com/athimmo.public/9472CL.jpg",
            "https://i4h6y2e7.stackpathcdn.com/athimmo.public/9472DL.jpg",
            "https://i4h6y2e7.stackpathcdn.com/athimmo.public/9472EL.jpg",
            "https://i4h6y2e7.stackpathcdn.com/athimmo.public/9472FL.jpg",
            "https://i4h6y2e7.stackpathcdn.com/athimmo.public/9472GL.jpg",
            "https://i4h6y2e7.stackpathcdn.com/athimmo.public/9472HL.jpg",
            "https://i4h6y2e7.stackpathcdn.com/athimmo.public/9472IL.jpg",
            "https://i4h6y2e7.stackpathcdn.com/athimmo.public/9472JL.jpg"
        ],
        "landlord_email": "info@athimmo.be",
        "landlord_name": "Athimmo",
        "landlord_phone": "068 28 26 80",
        "latitude": "50.6340400000000000000000000",
        "longitude": "3.7819690000000000000000000",
        "parking": true,
        "property_type": "apartment",
        "rent": 725,
        "room_count": 2,
        "terrace": true,
        "title": "Appartement 2 chambres 725 \u20ac + 80 \u20ac charges communes + 60 \u20ac provisions eau chaude et chauffage",
        "zipcode": "7800"
    },
    {
        "address": "Rue Isidore Hotton  28/1  7800ATH",
        "available_date": "2020-11-15",
        "city": "ATH",
        "currency": "EUR",
        "description": "A 300 m de la Grand'Place, +/- 1 km de la gare, appartement 1 chambre au rez-de-chauss\u00e9e, enti\u00e8rement r\u00e9nov\u00e9, spacieux et lumineux, avec un tr\u00e8s beau jardin (pas de charges communes) PEB E (386 kWh/m\u00b2.an) - 20170418015370\r\nDescription :\r\nRez : salon (13 m\u00b2), s\u00e9jour (23 m\u00b2), cuisine \u00e9quip\u00e9e - \u00e9vier simple bac, taques vitro, hotte \u00e0 charbon, frigo (6 m\u00b2), salle-de-douches -  douche, wc, 1 lavabo (5 m\u00b2), 1 chambre (14,30 m\u00b2), 1 cave \u00e0 l'arri\u00e8re gauche (11 m\u00b2)\r\nExt\u00e9rieur : tr\u00e8s beau jardin, terrasse\r\nLoyer : 670 \u20ac (pas de charges communes)\r\nLibre \u00e0 partir du 15 novembre 2020\r\n\r\n\r\n \r\n",
        "energy_label": "386 kWh/m\u00b2.an",
        "external_id": "2205",
        "external_images_count": 10,
        "external_link": "https://www.athimmo.be/fr/a-louer/ath/rdc-avec-jardin-1ch--670-\u20ac/2205",
        "external_source": "Athimmo2000Spider",
        "images": [
            "https://i4h6y2e7.stackpathcdn.com/athimmo.public/2205AL.jpg?637371513392440000",
            "https://i4h6y2e7.stackpathcdn.com/athimmo.public/2205BL.jpg?637371513326690000",
            "https://i4h6y2e7.stackpathcdn.com/athimmo.public/2205CL.jpg?637371513396870000",
            "https://i4h6y2e7.stackpathcdn.com/athimmo.public/2205DL.jpg?637371513513920000",
            "https://i4h6y2e7.stackpathcdn.com/athimmo.public/2205EL.jpg?637371513332540000",
            "https://i4h6y2e7.stackpathcdn.com/athimmo.public/2205FL.jpg?637371513339430000",
            "https://i4h6y2e7.stackpathcdn.com/athimmo.public/2205GL.jpg?637371513389010000",
            "https://i4h6y2e7.stackpathcdn.com/athimmo.public/2205HL.jpg?637371513482770000",
            "https://i4h6y2e7.stackpathcdn.com/athimmo.public/2205IL.jpg?637371513477910000",
            "https://i4h6y2e7.stackpathcdn.com/athimmo.public/2205JL.jpg?637371513486240000"
        ],
        "landlord_email": "info@athimmo.be",
        "landlord_name": "Athimmo",
        "landlord_phone": "068 28 26 80",
        "latitude": "50.6328900000000000000000000",
        "longitude": "3.7823490000000000000000000",
        "property_type": "apartment",
        "rent": 670,
        "room_count": 1,
        "terrace": true,
        "title": "Rdc avec jardin, 1ch. - 670 \u20ac",
        "zipcode": "7800"
    },
    {
        "address": "rue des Fr\u00e8res Descamps 48  7800ATH",
        "available_date": "2020-09-15",
        "city": "ATH",
        "currency": "EUR",
        "description": "Proche de la gare et du centre ville, chambre d'\u00e9tudiant \u00e0 louer (2\u00e8me \u00e9tage \u00e0 l'arri\u00e8re).\r\n\r\n",
        "external_id": "4338",
        "external_images_count": 1,
        "external_link": "https://www.athimmo.be/fr/a-louer/ath/chambre-detudiant-proche-de-la-gare-300-\u20ac/4338",
        "external_source": "Athimmo2000Spider",
        "images": [
            "https://i4h6y2e7.stackpathcdn.com/athimmo.public/4338AL.jpg"
        ],
        "landlord_email": "info@athimmo.be",
        "landlord_name": "Athimmo",
        "landlord_phone": "068 28 26 80",
        "latitude": "50.6275899000000000000000000",
        "longitude": "3.7758704000000000000000000",
        "property_type": "apartment",
        "rent": 300,
        "room_count": 1,
        "terrace": false,
        "title": "Chambre d'\u00e9tudiant, proche de la gare. 300 \u20ac",
        "zipcode": "7800"
    },
    {
        "address": "Route de Lessines 2/2  7800ATH",
        "available_date": "2021-01-01",
        "bathroom_count": 1,
        "city": "ATH",
        "currency": "EUR",
        "description": "Superbe appartement au rez-de-chauss\u00e9e, \u00e0 l'entr\u00e9e de la ville. Ensoleillement toute la journ\u00e9e, jardin et terrasse \u00e0 l'avant et \u00e0 l'arri\u00e8re. PEB  B (145 kWh/m\u00b2.an) - PEB-04002-R\r\nDescription :\r\nRez-de-chauss\u00e9e : Hall, WC, buanderie, s\u00e9jour avec cuisine \u00e9quip\u00e9e, SDB, 1chambre, jardins priv\u00e9s avec terrasse \u00e0 l'avant et \u00e0 l'arri\u00e8re, emplacement parking ext\u00e9rieur.\r\nLoyer : 650 \u20ac + 80 \u20ac de charges communes\r\nLibre \u00e0 partir du 1er janvier 2021\r\n\r\n\r\n",
        "energy_label": "145 kWh/m\u00b2.an",
        "external_id": "4855",
        "external_images_count": 7,
        "external_link": "https://www.athimmo.be/fr/a-louer/ath/magnifique-appt-neuf--650-\u20ac--80-\u20ac-ch-com/4855",
        "external_source": "Athimmo2000Spider",
        "images": [
            "https://i4h6y2e7.stackpathcdn.com/athimmo.public/4855AL.jpg?637370742804880000",
            "https://i4h6y2e7.stackpathcdn.com/athimmo.public/4855BL.jpg?637369813900300000",
            "https://i4h6y2e7.stackpathcdn.com/athimmo.public/4855CL.jpg?637369813892480000",
            "https://i4h6y2e7.stackpathcdn.com/athimmo.public/4855DL.jpg?637369813962040000",
            "https://i4h6y2e7.stackpathcdn.com/athimmo.public/4855EL.jpg?637369813959900000",
            "https://i4h6y2e7.stackpathcdn.com/athimmo.public/4855FL.jpg?637369813906790000",
            "https://i4h6y2e7.stackpathcdn.com/athimmo.public/4855GL.jpg?637369814023320000"
        ],
        "landlord_email": "info@athimmo.be",
        "landlord_name": "Athimmo",
        "landlord_phone": "068 28 26 80",
        "latitude": "50.6520300000000000000000000",
        "longitude": "3.8061000000000000000000000",
        "parking": true,
        "property_type": "apartment",
        "rent": 650,
        "room_count": 1,
        "terrace": true,
        "title": "Magnifique appt NEUF - 650 \u20ac + 80 \u20ac ch com",
        "zipcode": "7800"
    },
    {
        "address": "Rue de Dendre  9  7800ATH",
        "available_date": "2020-09-01",
        "bathroom_count": 1,
        "city": "ATH",
        "currency": "EUR",
        "description": "Jolie maison de ville, parfaitement entretenue, avec garage ferm\u00e9. PEB D 310 kWh/m\u00b2.an - 20190423011530\r\nSitu\u00e9e dans une rue calme, \u00e0 300 m de la gare et de la Grand Place.\r\nDescription :\r\nRez : Hall, W.C., salon, salle \u00e0 manger, cuisine \u00e9quip\u00e9e\r\n1er \u00e9tage : salle de bains, 2 chambres\r\n2\u00e8me \u00e9tage : 1 grande chambre\r\n+ garage ferm\u00e9 et s\u00e9curis\u00e9 en face de la maison.\r\nLoyer : 700 \u20ac\r\nLibre \u00e0 partir du 1er septembre 2020\r\n\r\n\r\n\r\n",
        "energy_label": "310 kWh/m\u00b2.an",
        "external_id": "1713",
        "external_images_count": 14,
        "external_link": "https://www.athimmo.be/fr/a-louer/ath/jolie-maison-de-ville--700-\u20ac/1713",
        "external_source": "Athimmo2000Spider",
        "images": [
            "https://i4h6y2e7.stackpathcdn.com/athimmo.public/1713AL.jpg?637368735635390000",
            "https://i4h6y2e7.stackpathcdn.com/athimmo.public/1713BL.jpg?637368735706310000",
            "https://i4h6y2e7.stackpathcdn.com/athimmo.public/1713CL.jpg?637368735783140000",
            "https://i4h6y2e7.stackpathcdn.com/athimmo.public/1713DL.jpg?637368735778320000",
            "https://i4h6y2e7.stackpathcdn.com/athimmo.public/1713EL.jpg?637368735836290000",
            "https://i4h6y2e7.stackpathcdn.com/athimmo.public/1713FL.jpg?637368735728290000",
            "https://i4h6y2e7.stackpathcdn.com/athimmo.public/1713GL.jpg?637368735734040000",
            "https://i4h6y2e7.stackpathcdn.com/athimmo.public/1713HL.jpg?637368735831080000",
            "https://i4h6y2e7.stackpathcdn.com/athimmo.public/1713IL.jpg?637368735830930000",
            "https://i4h6y2e7.stackpathcdn.com/athimmo.public/1713JL.jpg?637368735871260000",
            "https://i4h6y2e7.stackpathcdn.com/athimmo.public/1713KL.jpg?637368735869110000",
            "https://i4h6y2e7.stackpathcdn.com/athimmo.public/1713LL.jpg?637368735614880000",
            "https://i4h6y2e7.stackpathcdn.com/athimmo.public/1713ML.jpg?637368735618170000",
            "https://i4h6y2e7.stackpathcdn.com/athimmo.public/1713NL.jpg?637368735786800000"
        ],
        "landlord_email": "info@athimmo.be",
        "landlord_name": "Athimmo",
        "landlord_phone": "068 28 26 80",
        "property_type": "house",
        "rent": 700,
        "room_count": 3,
        "terrace": false,
        "title": "Jolie maison de ville - 700 \u20ac",
        "zipcode": "7800"
    },
    {
        "address": "Cour Jean Zuallart 2 bte 4 2/4  7800ATH",
        "bathroom_count": 1,
        "city": "ATH",
        "currency": "EUR",
        "description": "Au centre d'un clos priv\u00e9, \u00e0 +/- 200 m\u00e8tres de la Grand'Place, de la gare\r\nBel appartement 2 chambres, spacieux et lumineux, neuf\r\nComposition : \r\n1er \u00c9tage: Hall d'entr\u00e9e (3.55 m\u00b2), living - s\u00e9jour (36.50 m\u00b2), cuisine \u00e9quip\u00e9e (8.50 m\u00b2) - \u00e9vier double bacs taques vitroc\u00e9ramiques hotte four frigo lave-vaisselle, buanderie (3.70 m\u00b2), \r\nd\u00e9gagement (2.50 m\u00b2), W.C. s\u00e9par\u00e9, hall de nuit (7.80 m\u00b2), salle de bains (3.90 m\u00b2) - douche et lavabo - 2 chambres ( 2 * 12.50 m\u00b2)\r\nExt\u00e9rieur : Terrasse (18 m\u00b2)\r\nSous-sol : emplacement de parking face \u00e0 l'ascenseur ( largeur 3 m\u00e8tres 80), cave (+/- 8 m\u00b2)\r\nPoint de vue Technique : Compteur bi horaire, double vitrage aluminium, VMC simple flux, appartement est pourvu de stores v\u00e9nitiens \u00e0 toutes les fen\u00eatres\r\nLoyer : 850 \u20ac + 90 \u20ac charges communes\r\nLibre Imm\u00e9diatement\r\n\r\n\r\n\r\n\r\n",
        "elevator": true,
        "external_id": "9205",
        "external_images_count": 12,
        "external_link": "https://www.athimmo.be/fr/a-louer/ath/appartement-2-chambres-850-\u20ac--90-\u20ac-charges-communes/9205",
        "external_source": "Athimmo2000Spider",
        "images": [
            "https://i4h6y2e7.stackpathcdn.com/athimmo.public/9205AL.jpg?637321312957000000",
            "https://i4h6y2e7.stackpathcdn.com/athimmo.public/9205BL.jpg?637321313087290000",
            "https://i4h6y2e7.stackpathcdn.com/athimmo.public/9205CL.jpg?637321312826280000",
            "https://i4h6y2e7.stackpathcdn.com/athimmo.public/9205DL.jpg?637321312828940000",
            "https://i4h6y2e7.stackpathcdn.com/athimmo.public/9205EL.jpg?637321312834210000",
            "https://i4h6y2e7.stackpathcdn.com/athimmo.public/9205FL.jpg?637321312893300000",
            "https://i4h6y2e7.stackpathcdn.com/athimmo.public/9205GL.jpg?637321312897760000",
            "https://i4h6y2e7.stackpathcdn.com/athimmo.public/9205HL.jpg?637321312889810000",
            "https://i4h6y2e7.stackpathcdn.com/athimmo.public/9205IL.jpg?637321312949690000",
            "https://i4h6y2e7.stackpathcdn.com/athimmo.public/9205JL.jpg?637321313092310000",
            "https://i4h6y2e7.stackpathcdn.com/athimmo.public/9205KL.jpg?637321313104640000",
            "https://i4h6y2e7.stackpathcdn.com/athimmo.public/9205LL.jpg?637321312956400000"
        ],
        "landlord_email": "info@athimmo.be",
        "landlord_name": "Athimmo",
        "landlord_phone": "068 28 26 80",
        "latitude": "50.6295000000000000000000000",
        "longitude": "3.7800720000000000000000000",
        "parking": true,
        "property_type": "apartment",
        "rent": 850,
        "room_count": 2,
        "terrace": true,
        "title": "Appartement 2 chambres 850 \u20ac + 90 \u20ac charges communes",
        "zipcode": "7800"
    },
    {
        "address": "Rue de Pintamont 52 bte 4a  7800ATH",
        "available_date": "2020-10-15",
        "bathroom_count": 1,
        "city": "ATH",
        "currency": "EUR",
        "description": "A deux pas de la Grand\u2019 Place et de la gare, superbe appartement 2 chambres en duplex avec vue sur le parc de l'administration communale. 3\u00e8me \u00e9tage avec ascenseur. PEB D 330 kWh/m\u00b2.an - 20120127006949\r\nComposition:\r\nSous-sol\u00a0: cave\r\n3\u00e8me \u00e9tage\u00a0: Cuisine super-\u00e9quip\u00e9e \u2013 \u00e9vier simple bac, taques vitroc\u00e9ramiques, hotte, four, chauffe-plats, frigo, cong\u00e9lateur, lave-vaisselle, r\u00e9serve, s\u00e9jour (30 m\u00b2),WC, SDD -  douche, lavabo, chambre (15m\u00b2)\r\n4\u00e8me \u00e9tage\u00a0: chambre avec dressing, SDB \u2013 bain, douche, lavabo, machine \u00e0 laver, s\u00e8che-linge\r\nLoyer: 725 \u20ac + 75\u20ac charges communes \r\nLibre \u00e0 partir du 15 octobre 2020\r\n\r\n\r\n",
        "elevator": true,
        "energy_label": "330 kWh/m\u00b2.an",
        "external_id": "4819",
        "external_images_count": 14,
        "external_link": "https://www.athimmo.be/fr/a-louer/ath/ath--superbe-appt-2-ch-en-duplex--725\u20ac---75-ch/4819",
        "external_source": "Athimmo2000Spider",
        "images": [
            "https://i4h6y2e7.stackpathcdn.com/athimmo.public/4819AL.jpg?637304009882570000",
            "https://i4h6y2e7.stackpathcdn.com/athimmo.public/4819BL.jpg?637304009892630000",
            "https://i4h6y2e7.stackpathcdn.com/athimmo.public/4819CL.jpg?637304009944720000",
            "https://i4h6y2e7.stackpathcdn.com/athimmo.public/4819DL.jpg?637304009948720000",
            "https://i4h6y2e7.stackpathcdn.com/athimmo.public/4819EL.jpg?637304009886160000",
            "https://i4h6y2e7.stackpathcdn.com/athimmo.public/4819FL.jpg?637304010129490000",
            "https://i4h6y2e7.stackpathcdn.com/athimmo.public/4819GL.jpg?637304010131860000",
            "https://i4h6y2e7.stackpathcdn.com/athimmo.public/4819HL.jpg?637304009954650000",
            "https://i4h6y2e7.stackpathcdn.com/athimmo.public/4819IL.jpg?637304010030090000",
            "https://i4h6y2e7.stackpathcdn.com/athimmo.public/4819JL.jpg?637304010036450000",
            "https://i4h6y2e7.stackpathcdn.com/athimmo.public/4819KL.jpg?637304010027450000",
            "https://i4h6y2e7.stackpathcdn.com/athimmo.public/4819LL.jpg?637304010088260000",
            "https://i4h6y2e7.stackpathcdn.com/athimmo.public/4819ML.jpg?637304010077870000",
            "https://i4h6y2e7.stackpathcdn.com/athimmo.public/4819NL.jpg?637304010082450000"
        ],
        "landlord_email": "info@athimmo.be",
        "landlord_name": "Athimmo",
        "landlord_phone": "068 28 26 80",
        "latitude": "50.6286600000000000000000000",
        "longitude": "3.7742400000000000000000000",
        "property_type": "apartment",
        "rent": 725,
        "room_count": 2,
        "terrace": false,
        "title": "ATH - Superbe appt 2 ch en duplex - 725\u20ac  + 75 ch",
        "zipcode": "7800"
    },
    {
        "address": "Haute 32/5  7800ATH",
        "city": "ATH",
        "currency": "EUR",
        "description": "Appartement 1 chambre, r\u00e9nov\u00e9, 1er occupation, lumineux, 3\u00e8me \u00e9tage sans ascenseur PEB B 143 kWh/m\u00b2.an - 20160719012088 \r\nA +/- 300 m\u00e8tres de la Grand'Place et de la gare\r\nComposition\r\n3\u00e8me \u00e9tage : Hall d'entr\u00e9e (3.70 m\u00b2), cuisine + s\u00e9jour (21 m\u00b2) - \u00e9vier simple bacs taques vitroc\u00e9ramiques hotte au charbon four frigo - 1 chambre (9.72 m\u00b2), salle de douche (4.72 m\u00b2) - Douche WC mobilier . \r\nPoint de vue technique: chaudi\u00e8re murale gaz avec production d'eau chaude, ch\u00e2ssis velux double vitrage\r\nLoyer : 495 \u20ac + 12.50 \u20ac pour l'abandon de recours et les charges communes \r\nLibre Imm\u00e9diatement\r\nBail de 3 ann\u00e9es obligatoire!\r\n\r\n",
        "elevator": true,
        "energy_label": "143 kWh/m\u00b2.an",
        "external_id": "9120",
        "external_images_count": 4,
        "external_link": "https://www.athimmo.be/fr/a-louer/ath/appartement-495-\u20ac--125-charges-communes-et-abandon-de-recours/9120",
        "external_source": "Athimmo2000Spider",
        "images": [
            "https://i4h6y2e7.stackpathcdn.com/athimmo.public/9120AL.jpg?637375824920390000",
            "https://i4h6y2e7.stackpathcdn.com/athimmo.public/9120BL.jpg?637375824656960000",
            "https://i4h6y2e7.stackpathcdn.com/athimmo.public/9120CL.jpg?637375824665320000",
            "https://i4h6y2e7.stackpathcdn.com/athimmo.public/9120DL.jpg?637375824718010000"
        ],
        "landlord_email": "info@athimmo.be",
        "landlord_name": "Athimmo",
        "landlord_phone": "068 28 26 80",
        "latitude": "50.6293200000000000000000000",
        "longitude": "3.7799690000000000000000000",
        "property_type": "apartment",
        "rent": 495,
        "room_count": 1,
        "terrace": false,
        "title": "Appartement 495 \u20ac + 12.5 charges communes et abandon de recours",
        "zipcode": "7800"
    },
    {
        "address": "Rue Robert Delange 3  7801VILLERS-SAINT-AMAND",
        "bathroom_count": 1,
        "city": "VILLERS-SAINT-AMAND",
        "currency": "EUR",
        "description": "Belle maison de plain-pied 3 chambres avec garage, terrasse et jardin\r\nSitu\u00e9e dans un chemin calme, proche des grands axes Tournai/Bruxelles/Mons, \u00e0 5 minutes du centre ville et des magasins\r\nVue arri\u00e8re privative sur un bois, orientation sud-ouest (couch\u00e9 de soleil)\r\nComposition :\r\nRez-de-chauss\u00e9e : Hall d'entr\u00e9e (7.37 m\u00b2), WC s\u00e9par\u00e9 (1.68 m\u00b2), vestiaire (1.09 m\u00b2), hall de nuit (4.17 m\u00b2), 3 chambres (9.72 13.87 et 13.44 m\u00b2), salle de bains (5.42 m\u00b2) - baignoire lavabo et WC - \r\ns\u00e9jour (32 m\u00b2), cuisine (15 m\u00b2) - \u00e9vier simple taques \u00e9lectriques hotte four frigo lave-vaisselle - cellier (2.51 m\u00b2), buanderie (5.87 m\u00b2), garage (19.57 m\u00b2)\r\nExt\u00e9rieur : terrasse (+/- 12 m\u00b2), chalet (7.50 m\u00b2), jardin\r\nCaract\u00e9ristiques : pr\u00e9sence d'un adoucisseur d'eau, fen\u00eatres \u00e9quip\u00e9e de volets dont les plus grands \u00e9lectriques, chauffage central au mazout \r\nLoyer : 850 \u20ac \r\nLibre Imm\u00e9diatement\r\nPEB D (339 KW/an) 20200730018927",
        "energy_label": "339 kWh/m\u00b2.an",
        "external_id": "10180",
        "external_images_count": 10,
        "external_link": "https://www.athimmo.be/fr/a-louer/villerssaintamand/belle-maison-de-plainpied-3-chambres-avec-garage-terrasse-et-jardin/10180",
        "external_source": "Athimmo2000Spider",
        "images": [
            "https://i4h6y2e7.stackpathcdn.com/athimmo.public/10180AL.jpg?637322185313600000",
            "https://i4h6y2e7.stackpathcdn.com/athimmo.public/10180BL.jpg?637322185361710000",
            "https://i4h6y2e7.stackpathcdn.com/athimmo.public/10180CL.jpg?637322185590610000",
            "https://i4h6y2e7.stackpathcdn.com/athimmo.public/10180DL.jpg?637322185704110000",
            "https://i4h6y2e7.stackpathcdn.com/athimmo.public/10180EL.jpg?637322185334450000",
            "https://i4h6y2e7.stackpathcdn.com/athimmo.public/10180FL.jpg?637322185485380000",
            "https://i4h6y2e7.stackpathcdn.com/athimmo.public/10180GL.jpg?637322185448960000",
            "https://i4h6y2e7.stackpathcdn.com/athimmo.public/10180HL.jpg?637322185466970000",
            "https://i4h6y2e7.stackpathcdn.com/athimmo.public/10180IL.jpg?637322185581420000",
            "https://i4h6y2e7.stackpathcdn.com/athimmo.public/10180JL.jpg?637322185612310000"
        ],
        "landlord_email": "info@athimmo.be",
        "landlord_name": "Athimmo",
        "landlord_phone": "068 28 26 80",
        "latitude": "50.6219400000000000000000000",
        "longitude": "3.7494300000000000000000000",
        "property_type": "house",
        "rent": 850,
        "room_count": 3,
        "terrace": true,
        "title": "Belle maison de plain-pied 3 chambres avec garage, terrasse et jardin 850 \u20ac",
        "zipcode": "7801"
    }
]